src/LDA_EM.py
src/LDA_Gibbs.py
src/__init__.py
LDA_project_19-1.5.dist-info/LICENSE
LDA_project_19-1.5.dist-info/METADATA
LDA_project_19-1.5.dist-info/WHEEL
LDA_project_19-1.5.dist-info/top_level.txt
LDA_project_19-1.5.dist-info/RECORD
