Metadata-Version: 2.1
Name: LDA-project-19
Version: 1.5
Summary: Latent Dirichlet Allocation
Home-page: https://github.com/mingjiezhao/LDA_final_project_SP2019
Author: Mingjie Zhao, Ziwei Zhu
Author-email: mz136@duke.edu
License: UNKNOWN
Platform: UNKNOWN
Classifier: Development Status :: 3 - Alpha
Classifier: Intended Audience :: Developers
Classifier: Topic :: Software Development :: Libraries :: Python Modules
Classifier: License :: OSI Approved :: MIT License
Classifier: Programming Language :: Python :: 3
Classifier: Programming Language :: Python :: 3.4
Classifier: Programming Language :: Python :: 3.5
Classifier: Programming Language :: Python :: 3.6
Requires-Python: >=3
